gstin_validator/__init__.py
gstin_validator/core.py
gstin_validator-0.1.2.dist-info/METADATA
gstin_validator-0.1.2.dist-info/WHEEL
gstin_validator-0.1.2.dist-info/RECORD
